{
  "win": {
    "x86_64": {
      "filename": "iwyu-0.25-win-x86_64.tar.zst",
      "path": "win\\x86_64\\iwyu-0.25-win-x86_64.tar.zst",
      "sha256": "942e26eb684d4eacbeee7f9bd951d4736bcfcb3b0c125e7432380e646830dbef",
      "size": 810366
    }
  },
  "linux": {
    "x86_64": {
      "filename": "iwyu-0.25-linux-x86_64.tar.zst",
      "path": "linux\\x86_64\\iwyu-0.25-linux-x86_64.tar.zst",
      "sha256": "ebca230c1b866b487f26823576ab76e320a4bd889ef99171ebbe0a49c23e1d4a",
      "size": 777486
    },
    "arm64": {
      "filename": "iwyu-0.25-linux-arm64.tar.zst",
      "path": "linux\\arm64\\iwyu-0.25-linux-arm64.tar.zst",
      "sha256": "65e9061ea78c6c505f5290b82925c0fa7bd385fdf783852b96ed68db7e78d9dc",
      "size": 766361
    }
  },
  "darwin": {
    "x86_64": {
      "filename": "iwyu-0.25-darwin-x86_64.tar.zst",
      "path": "darwin\\x86_64\\iwyu-0.25-darwin-x86_64.tar.zst",
      "sha256": "a9c90eb358852ad118a453276e68f18b89e01b53f3aaf48be0c8a0c3904efb42",
      "size": 540244
    },
    "arm64": {
      "filename": "iwyu-0.25-darwin-arm64.tar.zst",
      "path": "darwin\\arm64\\iwyu-0.25-darwin-arm64.tar.zst",
      "sha256": "670c46eabc3508b7bb07beb6d014121280a6ea9055729b437dfd78ecdb8f69c8",
      "size": 531971
    }
  }
}